{
    "type": "minecraft:notice",
    "title": {
        "extra": [
            {
                "color": "gold",
                "translate": "json.kards.dialog.paiku.yansheng.main.1127",
                "fallback": "不死图腾"
            }
        ],
        "color": "aqua",
        "bold": true,
        "translate": "json.kards.dialog.paiku.juntuan.shenghaikongju.523",
        "fallback": "10K "
    },
    "external_title": {
        "translate": "json.kards.dialog.first_join.1.71",
        "fallback": ""
    },
    "body": [
        {
            "type": "minecraft:item",
            "item": {
                "id": "music_disc_13"
            },
            "show_decorations": false,
            "show_tooltip": false
        },
        {
            "type": "minecraft:plain_message",
            "contents": {
                "color": "gold",
                "italic": false,
                "translate": "json.kards.dialog.paiku.main.222",
                "fallback": "装备牌"
            },
            "width": 1024
        },
        {
            "type": "minecraft:plain_message",
            "contents": {
                "color": "gray",
                "italic": false,
                "extra": [
                    {
                        "color": "gold",
                        "italic": false,
                        "translate": "json.kards.dialog.paiku.yansheng.main.1127",
                        "fallback": "不死图腾"
                    }
                ],
                "translate": "json.kards.dialog.paiku.zhuangbei.busituteng.1181",
                "fallback": "随机获得一个"
            },
            "width": 1024
        }
    ],
    "inputs": [],
    "can_close_with_escape": true,
    "action": {
        "label": {
            "color": "green",
            "translate": "json.kards.dialog.paiku.zhuangbei.bianxiehuosai.1180",
            "fallback": "返回§c装备§a牌库"
        },
        "action": {
            "type": "minecraft:show_dialog",
            "dialog": "kards:paiku/zhuangbei/main"
        }
    }
}